{"breakpointMobile":"600px","breakpointTablet":"768px","breakpointDesktop":"1220px","":"export {\n  colorPrimary","colorPrimaryLight":"#eaa79e","colorPrimaryFaded":"#ecbcb3","colorWarning":"#f4bd50","colorError":"#f45050","colorWhite":"#fff","colorUrl":"\"#0000EE\"","colorDarkBlue":"\"#334144\"","colorBlack100":"#000","colorBlack70":"#4f4f4f","colorBlack50":"#828282","colorBlack25":"#bdbdbd","colorBlack12":"#e0e0e0","colorBlack5":"#f2f2f2","colorGray50":"#949ea0","colorGray25":"#dfe5ea","colorGray10":"#f5f6f7","minimumModalSize":"27.5rem","borderRadiusSmall":"0.1875rem","borderRadiusMedium":"1.25rem","borderRadiusLarge":"3.125rem","gradientPrimary":"linear-gradient(270deg, #eaa79e 0%, #ecbcb3 100%)","gradientBlack":"linear-gradient(180deg, rgba(0, 0, 0, 0) 0%, black 89.5%)","spacingDefault":"1.25rem","spacingXl":"7.5rem","spacingL":"5rem","spacingM":"3.125rem","spacingS":"1.875rem","spacingS2":"1.38rem","spacingXs":"1rem","spacingXs2":"0.8rem","spacingXxs":"0.5rem","spacingXxxs":"0.1rem","buttonShadow":"0px 15px 20px 0px #eaa89f","modalShadow":"0px 15px 30px 0px rgba(0, 0, 0, 0.05)","}\n\n.hero {\n  font-size":"2.75rem","font-weight":"400","}\n\nh1 {\n  font-size":"2rem","}\n\nh2 {\n  font-size":"1.5rem","}\n\nh3 {\n  font-size":"1.125rem","}\n\nh4 {\n  font-size":"1rem","}\n\nh5 {\n  font-size":"0.875rem","}\n\nh6 {\n  font-size":"0.75rem","}\n\np {\n  font-size":"0.875rem","}\n\n.paragraph-small {\n  font-size":"0.75rem","}\n\nbutton {\n  font-size":"0.75rem","}\n\na {\n  font-size":"0.875rem","}\n\ncaption {\n  font-size":"0.75rem","color":"#828282","h1Size":"2rem","h2Size":"1.5rem","h3Size":"1.125rem","h4Size":"1rem","h5Size":"0.875rem","h6Size":"0.75rem","cardTitleSize":"1.25rem","defaultSize":"0.875rem","paragraphSize":"0.875rem","paragraphSmallSize":"0.75rem","buttonSize":"0.75rem","linkSize":"0.875rem","captionSize":"0.75rem","lightWeight":"300","regularWeight":"400","mediumWeight":"500","semiBoldWeight":"600","boldWeight":"700","inputSize":"0.8125rem","labelSize":"0.625rem"}